[
  {
    "topic": "featureFlag",
    "comment": "Validating carriers criteria to be used with Amadeus GDS search (default setting)",
    "conditions": {
      "all": []
    },
    "priority": 100,
    "event": {
      "type": "featureFlag",
      "params": {
        "key": "flights.amadeus.validatingCarriers",
        "value": {
          "included": [
            "A3",
            "EI",
            "VW",
            "AM",
            "AW",
            "8U",
            "AH",
            "3S",
            "KC",
            "UU",
            "BT",
            "KF",
            "BP",
            "2J",
            "TX",
            "3C",
            "3E",
            "XK",
            "HF",
            "EN",
            "K7",
            "NX",
            "MD",
            "KM",
            "MK",
            "9U",
            "SW",
            "PX",
            "4N",
            "P4",
            "HC",
            "JU",
            "HM",
            "VT",
            "TN",
            "NF",
            "UM",
            "TL",
            "AS",
            "AZ",
            "Z8",
            "Z7",
            "NH",
            "IZ",
            "OZ",
            "KP",
            "5O",
            "RC",
            "GR",
            "HZ",
            "YK",
            "AV",
            "LR",
            "2K",
            "9V",
            "J2",
            "AD",
            "UP",
            "PG",
            "JD",
            "B2",
            "BG",
            "NT",
            "BV",
            "OB",
            "1X",
            "SN",
            "FB",
            "VR",
            "QC",
            "KR",
            "K6",
            "9K",
            "BW",
            "KA",
            "CX",
            "KX",
            "5Z",
            "CI",
            "MU",
            "WX",
            "CC",
            "MN",
            "DE",
            "CM",
            "SS",
            "OU",
            "OK",
            "CU",
            "CY",
            "DZ",
            "B5",
            "ZE",
            "2D",
            "T3",
            "MS",
            "LY",
            "EL",
            "EK",
            "E7",
            "ET",
            "EY",
            "9F",
            "BR",
            "FN",
            "7V",
            "FJ",
            "AY",
            "5H",
            "FZ",
            "XY",
            "5F",
            "FA",
            "GA",
            "A9",
            "G3",
            "GF",
            "HR",
            "HU",
            "HA",
            "2L",
            "2L",
            "H9",
            "UO",
            "HX",
            "MR",
            "FI",
            "JY",
            "4O",
            "6H",
            "JL",
            "NU",
            "J9",
            "QD",
            "7C",
            "JQ",
            "3K",
            "GK",
            "3J",
            "HO",
            "RQ",
            "KQ",
            "KE",
            "KU",
            "B0",
            "TM",
            "LQ",
            "QV",
            "LA",
            "JJ",
            "XL",
            "PZ",
            "LP",
            "LI",
            "O2",
            "FC",
            "LM",
            "LO",
            "8L",
            "LG",
            "MH",
            "AE",
            "L6",
            "2M",
            "5G",
            "OM",
            "ME",
            "MW",
            "YM",
            "M9",
            "8M",
            "UB",
            "MJ",
            "RA",
            "NP",
            "DD",
            "Y7",
            "N4",
            "BJ",
            "OA",
            "WY",
            "8Q",
            "PK",
            "PE",
            "PR",
            "PU",
            "CG",
            "PD",
            "PW",
            "P0",
            "QR",
            "7H",
            "WZ",
            "AT",
            "BI",
            "RJ",
            "7R",
            "WB",
            "S7",
            "SV",
            "DV",
            "TR",
            "BB",
            "D2",
            "SC",
            "FM",
            "ZH",
            "3U",
            "MI",
            "3M",
            "H2",
            "GQ",
            "IE",
            "SZ",
            "SA",
            "9X",
            "UL",
            "2I",
            "XQ",
            "WG",
            "PY",
            "TA",
            "5U",
            "RO",
            "TG",
            "WE",
            "GS",
            "TV",
            "TJ",
            "9N",
            "TB",
            "OR",
            "TK",
            "PS",
            "B7",
            "U6",
            "UQ",
            "UT",
            "HY",
            "V4",
            "VJ",
            "VN",
            "VS",
            "VA",
            "UK",
            "V7",
            "VY",
            "WS",
            "WM",
            "7W",
            "YC",
            "YE",
            "Y6",
            "M0",
            "S0",
            "A8",
            "V5",
            "AW",
            "J7",
            "K7",
            "IK",
            "TC",
            "6C",
            "RM",
            "P2",
            "J5",
            "Q3",
            "UI",
            "BZ",
            "KR",
            "GM",
            "QG",
            "CC",
            "CQ",
            "XC",
            "C8",
            "B5",
            "EG",
            "FN",
            "5H",
            "F8",
            "OJ",
            "FQ",
            "FA",
            "H1",
            "HS",
            "QD",
            "7C",
            "WU",
            "LQ",
            "LK",
            "YL",
            "7Y",
            "VL",
            "MJ",
            "1NA",
            "9Y",
            "NO",
            "J3",
            "8P",
            "ZP",
            "P6",
            "2Z",
            "FP",
            "DP",
            "1PR",
            "QW",
            "8N",
            "DR",
            "F2",
            "K5",
            "GQ",
            "OW",
            "LC",
            "SG",
            "S6",
            "7E",
            "TW",
            "5U",
            "VZ",
            "9N",
            "T5",
            "U8",
            "V6",
            "V4",
            "VJ",
            "Y4",
            "B4",
            "Y2",
            "DU",
            "7P",
            "5O",
            "QU",
            "SI",
            "XR",
            "3R",
            "T3",
            "EMT",
            "6W",
            "J0",
            "5G",
            "E8",
            "W4",
            "WV",
            "WC",
            "X1"
          ]
        }
      }
    }
  },
  {
    "topic": "featureFlag",
    "comment": "List of enabled hotel providers (default setting)",
    "conditions": {
      "all": []
    },
    "priority": 100,
    "event": {
      "type": "featureFlag",
      "params": {
        "key": "hotels.providers",
        "value": [
          "EREVMAX",
          "AMADEUS"
        ]
      }
    }
  },
  {
    "topic": "featureFlag",
    "comment": "List of enabled flight providers (default setting)",
    "conditions": {
      "all": []
    },
    "priority": 100,
    "event": {
      "type": "featureFlag",
      "params": {
        "key": "flights.providers",
        "value": [
          "AC",
          "AMADEUS"
        ]
      }
    }
  },
  {
    "topic": "featureFlag",
    "comment": "Queueing officeID to be used to book flights with Amadeus",
    "conditions": {
      "all": []
    },
    "priority": 100,
    "event": {
      "type": "featureFlag",
      "params": {
        "key": "flights.amadeus.queuingOfficeId",
        "value": ""
      }
    }
  },
  {
    "topic": "featureFlag",
    "comment": "OfficeID to be used to transfer ownership to when booking flights with Amadeus",
    "conditions": {
      "all": []
    },
    "priority": 100,
    "event": {
      "type": "featureFlag",
      "params": {
        "key": "flights.amadeus.ownerOfficeId",
        "value": ""
      }
    }
  }
]
